folium_magic/__init__.py
folium_magic/folium_magic.py
folium_magic/folium_tools.py
ipython_magic_folium-0.0.8.dist-info/LICENSE
ipython_magic_folium-0.0.8.dist-info/METADATA
ipython_magic_folium-0.0.8.dist-info/WHEEL
ipython_magic_folium-0.0.8.dist-info/top_level.txt
ipython_magic_folium-0.0.8.dist-info/RECORD
