Metadata-Version: 2.2
Name: ipython_magic_folium
Version: 0.0.8
License-File: LICENSE
Requires-Dist: folium
Requires-Dist: fiona
Requires-Dist: geocoder
Requires-Dist: branca
Dynamic: requires-dist
